ampel_knopf.v
module Ampel_Behavioral (
    input clk,
    input [2:0] counter,
    input knopf,
    output reg [1:0] ampelfarbe
);
    reg wunsch_signalisiert = 0;
    reg [3:0] wie_lange_noch_rot = 4'b1000;

    // Ampelfarbe berechnen (wie bisher)
    function [1:0] ampel_farbe(input [2:0] c);
        ampel_farbe = { 
            (~c[0] & ~c[1]) | (c[0] & c[1] & ~c[2]),
            (~c[0] & ~c[1] & ~c[2]) | (c[0] & c[2]) | (~c[0] & c[1] & c[2])
        };
    endfunction

    always @(posedge clk) begin
        // Wunsch vormerken, aber noch nicht aktivieren
        if (knopf)
            wunsch_signalisiert <= 1'b1;

        // Rotverlängerung läuft
        if (wie_lange_noch_rot != 4'b1000) begin
            ampelfarbe <= 2'b10; // Rot
            if (wie_lange_noch_rot == 4'b0001) begin
                wie_lange_noch_rot <= 4'b1000;
                wunsch_signalisiert <= 0;
            end else begin
                wie_lange_noch_rot <= wie_lange_noch_rot - 1'b1;
            end
        end
        // Normale Ampelsteuerung
        else begin
            // Prüfe, ob jetzt Rotphase beginnt UND Wunsch signalisiert ist
            if (ampel_farbe(counter) == 2'b10 && wunsch_signalisiert) begin
                wie_lange_noch_rot <= 4'b0111; // 7 Takte Rotverlängerung
                ampelfarbe <= 2'b10; // Rot
                // wunsch_signalisiert bleibt 1 bis Rotverlängerung beendet
            end else begin
                ampelfarbe <= ampel_farbe(counter);
            end
        end
    end
endmodule

module main ();
    reg clk = 1;
    reg [2:0] cntr = 0;
    reg knopf = 0;
    wire [1:0] ampelfarbe_Behavioral;

    Ampel_Behavioral ampel_Behavioral_inst (.clk(clk), .counter(cntr), .knopf(knopf), .ampelfarbe(ampelfarbe_Behavioral));

    initial begin
        $dumpfile("testbench.vcd");
        $dumpvars;
        #1;
        $display("Initial: Clock: %b, Counter: %b, Knopf: %b, Ampel_Behavioral: %b",
            clk, cntr, knopf, ampelfarbe_Behavioral);

        // Knopf einmal bei Grün drücken (z.B. bei cntr==0)
        #60;
        knopf = 1;
        #10;
        knopf = 0;

        // Knopf einmal bei Rot drücken (z.B. bei cntr==7)
        wait (cntr == 7);
        #1;
        knopf = 1;
        #10;
        knopf = 0;
    end

    always #50 clk = ~clk;
    always @(posedge clk) begin
        cntr = cntr + 1;
        #1
        $display("Clock: %b, Counter: %b, Knopf: %b, Ampel_Behavioral: %b",
            clk, cntr, knopf, ampelfarbe_Behavioral);
    end
    always @(posedge knopf) begin
        $display("Knopf gedrückt bei Counter: %b", cntr);
        $display("Aktuelle Ampelfarbe: %b", ampelfarbe_Behavioral);
    end
    initial #4000 $finish;
endmodule

testbench.vcd
$date
	Thu Jun  5 16:19:06 2025
$end
$version
	Icarus Verilog
$end
$timescale
	1s
$end
$scope module main $end
$var wire 2 ! ampelfarbe_Behavioral [1:0] $end
$var reg 1 " clk $end
$var reg 3 # cntr [2:0] $end
$var reg 1 $ knopf $end
$scope module ampel_Behavioral_inst $end
$var wire 1 " clk $end
$var wire 3 % counter [2:0] $end
$var wire 1 $ knopf $end
$var reg 2 & ampelfarbe [1:0] $end
$var reg 4 ' wie_lange_noch_rot [3:0] $end
$var reg 1 ( wunsch_signalisiert $end
$scope function ampel_farbe $end
$var reg 3 ) c [2:0] $end
$upscope $end
$upscope $end
$upscope $end
$enddefinitions $end
#0
$dumpvars
b0 )
0(
b1000 '
b11 &
b0 %
0$
b0 #
1"
b11 !
$end
#50
0"
#61
1$
#71
0$
#100
b1 #
b1 %
1"
#150
0"
#200
b0 !
b0 &
b10 )
b10 #
b10 %
1"
#250
0"
#300
b10 !
b10 &
b11 )
b11 #
b11 %
1"
#350
0"
#400
b100 )
b100 #
b100 %
1"
#450
0"
#500
b1 !
b1 &
b101 )
b101 #
b101 %
1"
#550
0"
#600
b110 )
b110 #
b110 %
1"
#650
0"
#700
b111 )
b111 #
b111 %
1"
#701
1$
#711
0$
#750
0"
#800
b11 !
b11 &
b0 )
b0 #
b0 %
1"
#850
0"
#900
b0 !
b0 &
b1 )
b1 #
b1 %
1"
#950
0"
#1000
b10 )
b10 #
b10 %
1"
#1050
0"
#1100
b10 !
b10 &
b11 )
b11 #
b11 %
1"
#1150
0"
#1200
b100 )
b100 #
b100 %
1"
#1250
0"
#1300
b1 !
b1 &
b101 )
b101 #
b101 %
1"
#1350
0"
#1400
b110 )
b110 #
b110 %
1"
#1450
0"
#1500
b111 )
b111 #
b111 %
1"
#1550
0"
#1600
b11 !
b11 &
b0 )
b0 #
b0 %
1"
#1650
0"
#1700
b0 !
b0 &
b1 )
b1 #
b1 %
1"
#1750
0"
#1800
b10 )
b10 #
b10 %
1"
#1850
0"
#1900
b10 !
b10 &
b11 )
b11 #
b11 %
1"
#1950
0"
#2000
b100 )
b100 #
b100 %
1"
#2050
0"
#2100
b1 !
b1 &
b101 )
b101 #
b101 %
1"
#2150
0"
#2200
b110 )
b110 #
b110 %
1"
#2250
0"
#2300
b111 )
b111 #
b111 %
1"
#2350
0"
#2400
b11 !
b11 &
b0 )
b0 #
b0 %
1"
#2450
0"
#2500
b0 !
b0 &
b1 )
b1 #
b1 %
1"
#2550
0"
#2600
b10 )
b10 #
b10 %
1"
#2650
0"
#2700
b10 !
b10 &
b11 )
b11 #
b11 %
1"
#2750
0"
#2800
b100 )
b100 #
b100 %
1"
#2850
0"
#2900
b1 !
b1 &
b101 )
b101 #
b101 %
1"
#2950
0"
#3000
b110 )
b110 #
b110 %
1"
#3050
0"
#3100
b111 )
b111 #
b111 %
1"
#3150
0"
#3200
b11 !
b11 &
b0 )
b0 #
b0 %
1"
#3250
0"
#3300
b0 !
b0 &
b1 )
b1 #
b1 %
1"
#3350
0"
#3400
b10 )
b10 #
b10 %
1"
#3450
0"
#3500
b10 !
b10 &
b11 )
b11 #
b11 %
1"
#3550
0"
#3600
b100 )
b100 #
b100 %
1"
#3650
0"
#3700
b1 !
b1 &
b101 )
b101 #
b101 %
1"
#3750
0"
#3800
b110 )
b110 #
b110 %
1"
#3850
0"
#3900
b111 )
b111 #
b111 %
1"
#3950
0"
#4000
b11 !
b11 &
b0 )
b0 #
b0 %
1"
